main.py
traveler-0.1.0.dist-info/licenses/LICENSE
traveler-0.1.0.dist-info/METADATA
traveler-0.1.0.dist-info/WHEEL
traveler-0.1.0.dist-info/top_level.txt
traveler-0.1.0.dist-info/RECORD
