Metadata-Version: 2.4
Name: traveler
Version: 0.1.0
Summary: A package for greetings
Requires-Python: >=3.12
License-File: LICENSE
Dynamic: license-file
